mutable_defaults.py
flake8_mutable-1.1.0.dist-info/DESCRIPTION.rst
flake8_mutable-1.1.0.dist-info/entry_points.txt
flake8_mutable-1.1.0.dist-info/METADATA
flake8_mutable-1.1.0.dist-info/metadata.json
flake8_mutable-1.1.0.dist-info/pbr.json
flake8_mutable-1.1.0.dist-info/RECORD
flake8_mutable-1.1.0.dist-info/top_level.txt
flake8_mutable-1.1.0.dist-info/WHEEL
