Metadata-Version: 2.0
Name: flake8-mutable
Version: 1.1.0
Summary: mutable defaults flake8 extension
Home-page: https://github.com/ebeweber/flake8-mutable
Author: Matthew Ebeweber
Author-email: mebeweber@gmail.com
License: MIT
Keywords: flake8 mutable arg kwarg
Platform: UNKNOWN
Requires-Dist: flake8
